dagster_cloud/__init__.py
dagster_cloud/constants.py
dagster_cloud/py.typed
dagster_cloud/version.py
dagster_cloud/agent/__init__.py
dagster_cloud/agent/dagster_cloud_agent.py
dagster_cloud/agent/queries.py
dagster_cloud/agent/cli/__init__.py
dagster_cloud/anomaly_detection/__init__.py
dagster_cloud/anomaly_detection/defs.py
dagster_cloud/anomaly_detection/mutation.py
dagster_cloud/anomaly_detection/types.py
dagster_cloud/api/__init__.py
dagster_cloud/api/dagster_cloud_api.py
dagster_cloud/artifacts/__init__.py
dagster_cloud/auth/__init__.py
dagster_cloud/auth/constants.py
dagster_cloud/batching/__init__.py
dagster_cloud/batching/batcher.py
dagster_cloud/dagster_insights/__init__.py
dagster_cloud/dagster_insights/errors.py
dagster_cloud/dagster_insights/insights_utils.py
dagster_cloud/dagster_insights/metrics_utils.py
dagster_cloud/dagster_insights/query.py
dagster_cloud/dagster_insights/bigquery/__init__.py
dagster_cloud/dagster_insights/bigquery/bigquery_utils.py
dagster_cloud/dagster_insights/bigquery/dbt_wrapper.py
dagster_cloud/dagster_insights/bigquery/insights_bigquery_resource.py
dagster_cloud/dagster_insights/snowflake/__init__.py
dagster_cloud/dagster_insights/snowflake/dagster_snowflake_insights.py
dagster_cloud/dagster_insights/snowflake/dbt_wrapper.py
dagster_cloud/dagster_insights/snowflake/definitions.py
dagster_cloud/dagster_insights/snowflake/insights_snowflake_resource.py
dagster_cloud/dagster_insights/snowflake/snowflake_utils.py
dagster_cloud/definitions/__init__.py
dagster_cloud/definitions/job_selection.py
dagster_cloud/execution/__init__.py
dagster_cloud/execution/cloud_run_launcher/__init__.py
dagster_cloud/execution/cloud_run_launcher/k8s.py
dagster_cloud/execution/cloud_run_launcher/process.py
dagster_cloud/execution/monitoring/__init__.py
dagster_cloud/execution/utils/__init__.py
dagster_cloud/execution/utils/process.py
dagster_cloud/instance/__init__.py
dagster_cloud/instrumentation/__init__.py
dagster_cloud/metadata/__init__.py
dagster_cloud-1.12.13.dist-info/METADATA
dagster_cloud-1.12.13.dist-info/WHEEL
dagster_cloud-1.12.13.dist-info/top_level.txt
dagster_cloud-1.12.13.dist-info/RECORD
