Metadata-Version: 2.4
Name: dagster-cloud
Version: 1.12.13
Author-email: Elementl <support@elementl.com>
License: Apache-2.0
Project-URL: Homepage, https://dagster.io/cloud
Project-URL: GitHub, https://github.com/dagster-io/dagster-cloud
Project-URL: Changelog, https://github.com/dagster-io/dagster-cloud/blob/main/CHANGES.md
Project-URL: Issue Tracker, https://github.com/dagster-io/dagster-cloud/issues
Project-URL: Twitter, https://twitter.com/dagster
Project-URL: LinkedIn, https://www.linkedin.com/showcase/dagster
Project-URL: YouTube, https://www.youtube.com/channel/UCfLnv9X8jyHTe6gJ4hVBo9Q
Project-URL: Slack, https://dagster.io/slack
Project-URL: Blog, https://dagster.io/blog
Project-URL: Newsletter, https://dagster.io/newsletter-signup
Classifier: Development Status :: 5 - Production/Stable
Classifier: Environment :: Console
Classifier: Environment :: Web Environment
Classifier: Intended Audience :: Developers
Classifier: Intended Audience :: System Administrators
Classifier: Programming Language :: Python :: 3.9
Classifier: Programming Language :: Python :: 3.10
Classifier: Programming Language :: Python :: 3.11
Classifier: Programming Language :: Python :: 3.12
Classifier: Programming Language :: Python :: 3.13
Classifier: Programming Language :: Python :: 3.14
Classifier: License :: OSI Approved :: Apache Software License
Classifier: Topic :: System :: Monitoring
Classifier: Topic :: Software Development :: Libraries :: Application Frameworks
Classifier: Operating System :: OS Independent
Requires-Python: <3.15,>=3.9
Requires-Dist: dagster==1.12.13
Requires-Dist: dagster-shared==1.12.13
Requires-Dist: dagster-cloud-cli==1.12.13
Requires-Dist: pex<2.60.0,>=2.1.132
Requires-Dist: questionary
Requires-Dist: requests
Requires-Dist: typer
Provides-Extra: tests
Requires-Dist: docker; extra == "tests"
Requires-Dist: httpretty; extra == "tests"
Requires-Dist: isort; extra == "tests"
Requires-Dist: freezegun; extra == "tests"
Requires-Dist: wordcloud; extra == "tests"
Requires-Dist: kubernetes; extra == "tests"
Requires-Dist: moto[all]; extra == "tests"
Requires-Dist: mypy; extra == "tests"
Requires-Dist: psutil; extra == "tests"
Requires-Dist: pylint; extra == "tests"
Requires-Dist: pytest; extra == "tests"
Requires-Dist: types-PyYAML; extra == "tests"
Requires-Dist: types-requests; extra == "tests"
Requires-Dist: dbt-bigquery>=1.9.0; extra == "tests"
Requires-Dist: dbt-core; extra == "tests"
Requires-Dist: dbt-snowflake; extra == "tests"
Requires-Dist: dbt-duckdb; extra == "tests"
Requires-Dist: dagster-dbt; extra == "tests"
Requires-Dist: dagster-k8s; extra == "tests"
Requires-Dist: dagster-docker; extra == "tests"
Requires-Dist: dagster-cloud-backend; extra == "tests"
Requires-Dist: dagster-test; extra == "tests"
Requires-Dist: dagster-cloud-test-infra; extra == "tests"
Requires-Dist: dagster-cloud-dagit; extra == "tests"
Requires-Dist: dagster-dg-cli; extra == "tests"
Requires-Dist: syrupy; extra == "tests"
Provides-Extra: insights
Requires-Dist: pyarrow; extra == "insights"
Provides-Extra: docker
Requires-Dist: docker; extra == "docker"
Requires-Dist: dagster-docker==0.28.13; extra == "docker"
Provides-Extra: kubernetes
Requires-Dist: kubernetes; extra == "kubernetes"
Requires-Dist: dagster-k8s==0.28.13; extra == "kubernetes"
Provides-Extra: ecs
Requires-Dist: dagster-aws==0.28.13; extra == "ecs"
Requires-Dist: boto3; extra == "ecs"
Provides-Extra: sandbox
Requires-Dist: supervisor; extra == "sandbox"
Provides-Extra: pex
Requires-Dist: boto3; extra == "pex"
Provides-Extra: serverless
Requires-Dist: boto3; extra == "serverless"
